GeeksforgeeksTheoryOfComputationAndAutomataLectureNotes/README.md
GeeksforgeeksTheoryOfComputationAndAutomataLectureNotes/__init__.py
GeeksforgeeksTheoryOfComputationAndAutomataLectureNotes/__main__.py
GeeksforgeeksTheoryOfComputationAndAutomataLectureNotes/file.epub
GeeksforgeeksTheoryOfComputationAndAutomataLectureNotes/index.html
GeeksforgeeksTheoryOfComputationAndAutomataLectureNotes/css/__init__.py
GeeksforgeeksTheoryOfComputationAndAutomataLectureNotes/css/annotations.css
GeeksforgeeksTheoryOfComputationAndAutomataLectureNotes/css/main.css
GeeksforgeeksTheoryOfComputationAndAutomataLectureNotes/css/normalize.css
GeeksforgeeksTheoryOfComputationAndAutomataLectureNotes/css/popup.css
GeeksforgeeksTheoryOfComputationAndAutomataLectureNotes/font/__init__.py
GeeksforgeeksTheoryOfComputationAndAutomataLectureNotes/font/fontello.eot
GeeksforgeeksTheoryOfComputationAndAutomataLectureNotes/font/fontello.svg
GeeksforgeeksTheoryOfComputationAndAutomataLectureNotes/font/fontello.ttf
GeeksforgeeksTheoryOfComputationAndAutomataLectureNotes/font/fontello.woff
GeeksforgeeksTheoryOfComputationAndAutomataLectureNotes/img/__init__.py
GeeksforgeeksTheoryOfComputationAndAutomataLectureNotes/img/annotator-glyph-sprite.png
GeeksforgeeksTheoryOfComputationAndAutomataLectureNotes/img/annotator-icon-sprite.png
GeeksforgeeksTheoryOfComputationAndAutomataLectureNotes/img/apple-touch-icon.png
GeeksforgeeksTheoryOfComputationAndAutomataLectureNotes/img/cancelfullscreen.png
GeeksforgeeksTheoryOfComputationAndAutomataLectureNotes/img/close.png
GeeksforgeeksTheoryOfComputationAndAutomataLectureNotes/img/fullscreen.png
GeeksforgeeksTheoryOfComputationAndAutomataLectureNotes/img/loader.gif
GeeksforgeeksTheoryOfComputationAndAutomataLectureNotes/img/menu-icon.png
GeeksforgeeksTheoryOfComputationAndAutomataLectureNotes/img/save.png
GeeksforgeeksTheoryOfComputationAndAutomataLectureNotes/img/saved.png
GeeksforgeeksTheoryOfComputationAndAutomataLectureNotes/img/settings-s.png
geeksforgeeks_theory_of_computation_and_automata_lecture_notes-2024.3.3.0.dist-info/METADATA
geeksforgeeks_theory_of_computation_and_automata_lecture_notes-2024.3.3.0.dist-info/WHEEL
geeksforgeeks_theory_of_computation_and_automata_lecture_notes-2024.3.3.0.dist-info/entry_points.txt
geeksforgeeks_theory_of_computation_and_automata_lecture_notes-2024.3.3.0.dist-info/top_level.txt
geeksforgeeks_theory_of_computation_and_automata_lecture_notes-2024.3.3.0.dist-info/RECORD
